liftover/__init__.py
liftover/chain_file.cp310-win_amd64.pyd
liftover/download_file.py
liftover/lifter.py
liftover-1.3.3.dist-info/licenses/LICENSE.txt
liftover-1.3.3.dist-info/METADATA
liftover-1.3.3.dist-info/WHEEL
liftover-1.3.3.dist-info/top_level.txt
liftover-1.3.3.dist-info/RECORD
