Metadata-Version: 2.4
Name: liftover
Version: 1.3.3
Summary: Package for converting between genome build coordinates
Home-page: https://github.com/jeremymcrae/liftover
Author: Jeremy McRae
Author-email: jmcrae@illumina.com
License: MIT
Classifier: Development Status :: 4 - Beta
Classifier: Topic :: Scientific/Engineering :: Bio-Informatics
License-File: LICENSE.txt
Requires-Dist: urllib3
Dynamic: author
Dynamic: author-email
Dynamic: classifier
Dynamic: description
Dynamic: description-content-type
Dynamic: home-page
Dynamic: license
Dynamic: license-file
Dynamic: requires-dist
Dynamic: summary
